flet_icon/__init__.py
flet_icon/app.py
flet_icon-0.3.dist-info/entry_points.txt
flet_icon-0.3.dist-info/LICENSE.txt
flet_icon-0.3.dist-info/METADATA
flet_icon-0.3.dist-info/WHEEL
flet_icon-0.3.dist-info/RECORD
