Metadata-Version: 2.1
Name: flet-icon
Version: 0.3
Summary: a collection of icons for flutter as flet
License: MIT
Keywords: packaging,flet,flet-icon,flutter,icon
Author: Tai
Author-email: 1174501146@qq.com
Requires-Python: >=3.10,<4.0
Classifier: License :: OSI Approved :: MIT License
Classifier: Operating System :: OS Independent
Classifier: Programming Language :: Python :: 3
Classifier: Programming Language :: Python :: 3.10
Classifier: Programming Language :: Python :: 3.11
Classifier: Programming Language :: Python :: 3
Classifier: Programming Language :: Python :: 3.7
Classifier: Programming Language :: Python :: 3.8
Requires-Dist: flet (>=0.4.2,<0.5.0)
Requires-Dist: pyperclip (>=1.8.2,<2.0.0)
